[{"tile": "CA_SierraNevada_9_2022", "error": "Expecting value: line 1 column 1 (char 0)"}, {"args": ["pdal", "info", "--all", "--driver", "readers.ept", "--readers.ept.resolution=800.0", "--readers.ept.threads=6", "--filters.hexbin.edge_size=1000", "--filters.hexbin.threshold=1", "https://s3-us-west-2.amazonaws.com/usgs-lidar-public/NM_SouthEast_B5_2018/ept.json"], "error": "Unexpected error 9 on netlink descriptor 9.\n"}, {"tile": "TX_Lower_SanBernard_B3_2017", "error": "Expecting value: line 1 column 1 (char 0)"}, {"args": ["pdal", "info", "--all", "--driver", "readers.ept", "--readers.ept.resolution=800.0", "--readers.ept.threads=6", "--filters.hexbin.edge_size=1000", "--filters.hexbin.threshold=1", "https://s3-us-west-2.amazonaws.com/usgs-lidar-public/USGS_LPC_AR_Ouachita_B3_2016_LAS_2018/ept.json"], "error": "(pdal info readers.ept Warning) Failed to read 1-1-1-1: readers.las: Invalid file signature. Was expecting 'LASF', Check the first four  bytes of the file.\n(pdal info readers.ept Warning) Failed to read 1-1-0-0: readers.las: Invalid version 1205840880 found in LAZ chunk table.\n(pdal info readers.ept Warning) Failed to read 1-1-1-0: readers.las: Invalid version 1337961456 found in LAZ chunk table.\n(pdal info readers.ept Warning) Use readers.ept.ignore_unreadable to ignore this error\nPDAL: readers.ept: Error reading tile 1-1-1-1: readers.las: Invalid file signature. Was expecting 'LASF', Check the first four  bytes of the file.\n\n"}, {"error": "ParseException: Expected word but encountered end of stream"}, {"error": "ParseException: Expected word but encountered end of stream"}, {"tile": "USGS_LPC_WA_Western_North_2016_LAS_2018", "error": "Expecting value: line 1 column 1 (char 0)"}, {"tile": "USGS_LPC_WA_Western_South_2016_LAS_2018", "error": "Expecting value: line 1 column 1 (char 0)"}]